bench_icarus/th23.v
module th23(a, b, c, th);

input wire a, b, c;
output reg th;

initial th <= 0;

wire #10 th_set = ((a&b)|(a&c)|(b&c));
wire #10 th_res = ((a==0)&(b==0)&(c==0));

always @(th_set or th_res) begin
	if(th_res) begin
		#10 th <= 1'b0;
	end 
	if(th_set)begin
		#10 th <= 1'b1;
	end
end

endmodule

bench_icarus/thfadd.v
module thfadd(x0, x1, y0, y1, ci0, ci1, z0, z1, c0, c1);

input wire x0, x1, y0, y1, ci0, ci1;
output wire z0, z1, c0, c1;


wire w1, w2;

th23 th_0(ci0, x0, y0, c0);
th23 th_1(ci1, x1, y1, c1);

//assign c0 = w1;
//assign c1 = w2;

//assign z0 = 0;
//assign z1 = 0;


//th34w2 th_2(w2, ci0, y0, x0, z0);
//th34w2 th_3(w1, ci1, y1, x1, z1);

endmodule

trunk/bench_icarus/bench.v
`timescale 1ns / 100 ps

module testbench();

initial
begin
    $display("begin");

    $dumpfile("test.vcd");
    $dumpvars(0,testbench);
end

//not test
reg [2:0] comb;
reg isnull;

wire z0, z1, c0, c1;
wire ta0 = (isnull == 1) ? 0 : ~comb[0:0];
wire tb0 = (isnull == 1) ? 0 : ~comb[1:1];
wire tc0 = (isnull == 1) ? 0 : ~comb[2:2];

wire #10 ta1 = (isnull == 1) ? 0 : ~ta0;
wire #10 tb1 = (isnull == 1) ? 0 : ~tb0;
wire #10 tc1 = (isnull == 1) ? 0 : ~tc0;


thfadd th_0(ta0, ta1, tb0, tb1, tc0, tc1, z0, z1, c0, c1);

initial
begin
	isnull <=1;
	#50;
	comb <= 3'd0;
	isnull <=0;
	#100;
	isnull <=1;
	#50;
	comb <= 3'd1;
	isnull <=0;
	#100;
	isnull <=1;
	#50;
	comb <= 3'd2;
	isnull <=0;
	#100;
	isnull <=1;
	#50;
	comb <= 3'd3;
	isnull <=0;
	#100;
	isnull <=1;
	#50;
	comb <= 3'd4;
	isnull <=0;
	#100;
	isnull <=1;
	#50;
	comb <= 3'd5;
	isnull <=0;
	#100;
	isnull <=1;
	#50;
	comb <= 3'd6;
	isnull <=0;
	#100;
	isnull <=1;
	#50;
	comb <= 3'd7;
	isnull <=0;
	#100;
	isnull <=1;
	#50;

	
end


endmodule

trunk/bench_icarus/test.vcd
$date
	Mon Mar 02 22:06:14 2015
$end
$version
	Icarus Verilog
$end
$timescale
	100ps
$end
$scope module testbench $end
$var wire 1 ! z0 $end
$var wire 1 " z1 $end
$var wire 1 # tc1 $end
$var wire 1 $ tc0 $end
$var wire 1 % tb1 $end
$var wire 1 & tb0 $end
$var wire 1 ' ta1 $end
$var wire 1 ( ta0 $end
$var wire 1 ) c1 $end
$var wire 1 * c0 $end
$var reg 3 + comb [2:0] $end
$var reg 1 , isnull $end
$scope module th_0 $end
$var wire 1 $ ci0 $end
$var wire 1 # ci1 $end
$var wire 1 ( x0 $end
$var wire 1 ' x1 $end
$var wire 1 & y0 $end
$var wire 1 % y1 $end
$var wire 1 ! z0 $end
$var wire 1 " z1 $end
$var wire 1 ) c1 $end
$var wire 1 * c0 $end
$scope module th_0 $end
$var wire 1 $ a $end
$var wire 1 ( b $end
$var wire 1 & c $end
$var wire 1 - th_res $end
$var wire 1 . th_set $end
$var reg 1 * th $end
$upscope $end
$scope module th_1 $end
$var wire 1 # a $end
$var wire 1 ' b $end
$var wire 1 % c $end
$var wire 1 / th_res $end
$var wire 1 0 th_set $end
$var reg 1 ) th $end
$upscope $end
$upscope $end
$upscope $end
$enddefinitions $end
#0
$dumpvars
x0
x/
x.
x-
1,
bx +
0*
0)
0(
x'
0&
x%
0$
x#
z"
z!
$end
#100
0.
1-
0'
0%
0#
#200
00
1/
#500
1(
1&
1$
0,
b0 +
#600
1.
0-
#700
1*
#1500
0(
0&
0$
1,
#1600
0.
1-
#1700
0*
#2000
0(
1&
1$
0,
b1 +
#2100
1.
0-
1'
#2200
1*
0/
#3000
0&
0$
1,
#3100
0.
1-
0'
#3200
0*
1/
#3500
1(
0&
1$
0,
b10 +
#3600
1.
0-
1%
#3700
1*
0/
#4500
0(
0$
1,
#4600
0.
1-
0%
#4700
0*
1/
#5000
0(
1$
0,
b11 +
#5100
0-
1'
1%
#5200
10
0/
#5300
1)
#6000
0$
1,
#6100
1-
0'
0%
#6200
1/
00
#6300
0)
#6500
1(
1&
0$
0,
b100 +
#6600
1.
0-
1#
#6700
1*
0/
#7500
0(
0&
1,
#7600
1-
0.
0#
#7700
0*
1/
#8000
0(
1&
0,
b101 +
#8100
0-
1'
1#
#8200
10
0/
#8300
1)
#9000
0&
1,
#9100
1-
0'
0#
#9200
00
1/
#9300
0)
#9500
1(
0&
0,
b110 +
#9600
0-
1%
1#
#9700
10
0/
#9800
1)
#10500
0(
1,
#10600
1-
0%
0#
#10700
00
1/
#10800
0)
#11000
0(
0,
b111 +
#11100
1'
1%
1#
#11200
10
0/
#11300
1)
#12000
1,
#12100
0'
0%
0#
#12200
00
1/
#12300
0)
