trunk/modules/a_or.v
module a_or(a, b, out);

input wire a;
input wire b;
output wire out;

wire t_out;

assign #`reldelay t_out = ((a === 1'bz)||(b === 1'bz)) ? 1'bz : a | b;
assign out = (t_out === 1'bx) ? 1'bz : t_out; //чтобы убрать x состояние

endmodule

trunk/modules/a_hsum.v
module a_hsum(a, b, os, oc);

input wire a;
input wire b;
output wire os;
output wire oc;

wire t_os;
wire t_oc;

assign #`reldelay t_os = ((a === 1'bz)||(b === 1'bz)) ? 1'bz : a ^ b;
assign os = ((t_os === 1'bx)||(t_oc === 1'bx)) ? 1'bz : t_os; //чтобы убрать x состояние

assign #`reldelay t_oc = ((a === 1'bz)||(b === 1'bz)) ? 1'bz : a & b;
assign oc = ((t_os === 1'bx)||(t_oc === 1'bx)) ? 1'bz : t_oc; //чтобы убрать x состояние

endmodule

trunk/modules/a_fsum.v
module a_fsum(a, b, c, os, oc);

input wire a;
input wire b;
input wire c;
output wire os;
output wire oc;

wire t_os;
wire t_oc;

wire s1;
wire c1;
a_hsum hsum1(a, b, s1, c1);

wire c2;
a_hsum hsum2(c, s1, t_os, c2);

a_or aor(c2, c1, t_oc);

assign os = ((t_os===1'bz)||(t_oc===1'bz)) ? 1'bz : t_os;  //чтобы убрать x состояние
assign oc = ((t_os===1'bz)||(t_oc===1'bz)) ? 1'bz : t_oc; //чтобы убрать x состояние

endmodule

modules/a_xor.v
module a_xor(a, b, out);

input wire a;
input wire b;
output wire out;

wire t_out;

assign #`reldelay t_out = ((a === 1'bz)||(b === 1'bz)) ? 1'bz : a ^ b;
assign out = (t_out === 1'bx) ? 1'bz : t_out; //чтобы убрать x состояние

endmodule

trunk/modules/a_and.v
module a_and(a, b, out);

input wire a;
input wire b;
output wire out;

wire t_out;

assign #`reldelay t_out = ((a === 1'bz)||(b === 1'bz)) ? 1'bz : a & b;
assign out = (t_out === 1'bx) ? 1'bz : t_out; //чтобы убрать x состояние

endmodule

trunk/modules/a_not.v
module a_not(in, out);

input wire in;
output wire out;

wire t_out;

assign #`reldelay t_out = (in === 1'bz) ? 1'bz : ~in; //как бы одна релюха. срабатывает с задержкой
assign out = (t_out === 1'bx) ? 1'bz : t_out; //чтобы убрать x состояние

endmodule

bench_icarus/bench.v
`timescale 1ns / 100 ps
`define CLKHPeriod     1.0  // 1 ns
`define OneNS          1.0  // 1 ns или нс
`define OneUS       1000.0  // 1 us или мкс
`define OneMS    1000000.0  // 1 ms или мс
`define OneS  1000000000.0  // 1 ms или мс

`define reldelay 5 //время переключения реле

//1 MHz период такта 1us

module testbench();



initial
begin
    $display("begin");

    $dumpfile("test.vcd");
    $dumpvars(0,testbench);
end

//not test
reg  not_test;
wire not_test_result;
a_not a_not_module(not_test, not_test_result);

initial
begin
	not_test <= 1'bx;
	#50;
	not_test <= 1'bz;
	#50;
	not_test <= 1'b1;
	#50;
	not_test <= 1'bz;
	#50;
	not_test <= 1'b0;
	#50;
	not_test <= 1'bz;
	#50;
end

//and test
reg  and_test_a;
reg  and_test_b;
reg  and_test_c;
wire and_test_result;
a_and a_and_module(and_test_a, and_test_b, and_test_result);

wire or_test_result;
a_or a_or_module(and_test_a, and_test_b, or_test_result);

wire xor_test_result;
a_xor a_xor_module(and_test_a, and_test_b, xor_test_result);

wire hsum_test_result_s;
wire hsum_test_result_c;
a_hsum a_hsum_module(and_test_a, and_test_b, hsum_test_result_s, hsum_test_result_c);

wire fsum_test_result_s;
wire fsum_test_result_c;
a_fsum a_fsum_module(and_test_a, and_test_b, and_test_c, fsum_test_result_s, fsum_test_result_c);

initial
begin
	and_test_a <= 1'bx;
	and_test_b <= 1'bx;
	and_test_c <= 1'bx;	
	#50;
	and_test_a <= 1'bz;
	#50;
	and_test_b <= 1'bz;
	#50;
	and_test_c <= 1'bz;
	#50;
	and_test_a <= 1'b1;	
	#50;
	and_test_b <= 1'b1;
	#50;
	and_test_c <= 1'b0;
	#50;	
	and_test_a <= 1'bz;
	and_test_b <= 1'bz;
	#50;
	and_test_a <= 1'b1;	
	#50;
	and_test_b <= 1'b0;
	#50;	
	and_test_a <= 1'bz;
	and_test_b <= 1'bz;
	#50;
	and_test_a <= 1'b0;	
	#50;
	and_test_b <= 1'b1;
	#50;	
	and_test_a <= 1'bz;
	and_test_b <= 1'bz;
	#50;
	and_test_a <= 1'b0;	
	#50;
	and_test_b <= 1'b0;
	#50;	
	and_test_a <= 1'bz;
	and_test_b <= 1'bz;	
	#50;
	and_test_a <= 1'b1;	
	#50;
	and_test_b <= 1'b1;
	#50;
	and_test_c <= 1'b1;
	#50;	
	and_test_a <= 1'bz;
	and_test_b <= 1'bz;
	#50;
	and_test_a <= 1'b1;	
	#50;
	and_test_b <= 1'b0;
	#50;	
	and_test_a <= 1'bz;
	and_test_b <= 1'bz;
	#50;
	and_test_a <= 1'b0;	
	#50;
	and_test_b <= 1'b1;
	#50;	
	and_test_a <= 1'bz;
	and_test_b <= 1'bz;
	#50;
	and_test_a <= 1'b0;	
	#50;
	and_test_b <= 1'b0;
	#50;	
	and_test_a <= 1'bz;
	and_test_b <= 1'bz;
	and_test_c <= 1'bz;
	#50;
	and_test_a <= 1'bz;
	and_test_b <= 1'bz;
	and_test_c <= 1'bz;
	#50;
end

endmodule

trunk/bench_icarus/test.vcd
$date
	Wed Feb 11 20:44:57 2015
$end
$version
	Icarus Verilog
$end
$timescale
	100ps
$end
$scope module testbench $end
$var wire 1 ! xor_test_result $end
$var wire 1 " or_test_result $end
$var wire 1 # not_test_result $end
$var wire 1 $ hsum_test_result_s $end
$var wire 1 % hsum_test_result_c $end
$var wire 1 & fsum_test_result_s $end
$var wire 1 ' fsum_test_result_c $end
$var wire 1 ( and_test_result $end
$var reg 1 ) and_test_a $end
$var reg 1 * and_test_b $end
$var reg 1 + and_test_c $end
$var reg 1 , not_test $end
$scope module a_and_module $end
$var wire 1 ) a $end
$var wire 1 * b $end
$var wire 1 - t_out $end
$var wire 1 ( out $end
$upscope $end
$scope module a_fsum_module $end
$var wire 1 ) a $end
$var wire 1 * b $end
$var wire 1 + c $end
$var wire 1 . t_os $end
$var wire 1 / t_oc $end
$var wire 1 0 s1 $end
$var wire 1 & os $end
$var wire 1 ' oc $end
$var wire 1 1 c2 $end
$var wire 1 2 c1 $end
$scope module aor $end
$var wire 1 3 t_out $end
$var wire 1 / out $end
$var wire 1 2 b $end
$var wire 1 1 a $end
$upscope $end
$scope module hsum1 $end
$var wire 1 ) a $end
$var wire 1 * b $end
$var wire 1 4 t_os $end
$var wire 1 5 t_oc $end
$var wire 1 0 os $end
$var wire 1 2 oc $end
$upscope $end
$scope module hsum2 $end
$var wire 1 + a $end
$var wire 1 0 b $end
$var wire 1 6 t_os $end
$var wire 1 7 t_oc $end
$var wire 1 . os $end
$var wire 1 1 oc $end
$upscope $end
$upscope $end
$scope module a_hsum_module $end
$var wire 1 ) a $end
$var wire 1 * b $end
$var wire 1 8 t_os $end
$var wire 1 9 t_oc $end
$var wire 1 $ os $end
$var wire 1 % oc $end
$upscope $end
$scope module a_not_module $end
$var wire 1 , in $end
$var wire 1 : t_out $end
$var wire 1 # out $end
$upscope $end
$scope module a_or_module $end
$var wire 1 ) a $end
$var wire 1 * b $end
$var wire 1 ; t_out $end
$var wire 1 " out $end
$upscope $end
$scope module a_xor_module $end
$var wire 1 ) a $end
$var wire 1 * b $end
$var wire 1 < t_out $end
$var wire 1 ! out $end
$upscope $end
$upscope $end
$enddefinitions $end
#0
$dumpvars
x<
x;
x:
x9
x8
x7
x6
x5
x4
x3
z2
z1
z0
z/
z.
x-
x,
x+
x*
x)
z(
z'
z&
z%
z$
z#
z"
z!
$end
#50
z3
z6
z7
#500
z)
z,
#550
z-
z4
z5
z8
z9
z;
z<
z:
#1000
z*
1,
#1050
0#
0:
#1500
z+
z,
#1550
z#
z:
#2000
1)
0,
#2050
1#
1:
#2500
1*
z,
#2550
1(
00
12
0$
1%
1"
0!
z#
1-
04
15
08
19
1;
0<
z:
#3000
0+
#3050
0.
01
06
07
#3100
1'
0&
1/
13
#3500
z*
z)
#3550
z(
z0
z2
z$
z%
z"
z!
z-
z4
z5
z8
z9
z;
z<
#3600
z&
z'
z.
z1
z/
z6
z7
z3
#4000
1)
#4500
0*
#4550
0(
10
02
1$
0%
1"
1!
0-
14
05
18
09
1;
1<
#4600
1.
01
16
07
#4650
0'
1&
0/
03
#5000
z*
z)
#5050
z(
z0
z2
z$
z%
z"
z!
z-
z4
z5
z8
z9
z;
z<
#5100
z&
z'
z.
z1
z/
z6
z7
z3
#5500
0)
#6000
1*
#6050
0(
10
02
1$
0%
1"
1!
0-
14
05
18
09
1;
1<
#6100
1.
01
16
07
#6150
0'
1&
0/
03
#6500
z*
z)
#6550
z(
z0
z2
z$
z%
z"
z!
z-
z4
z5
z8
z9
z;
z<
#6600
z&
z'
z.
z1
z/
z6
z7
z3
#7000
0)
#7500
0*
#7550
0(
00
02
0$
0%
0"
0!
0-
04
05
08
09
0;
0<
#7600
0.
01
06
07
#7650
0'
0&
0/
03
#8000
z*
z)
#8050
z(
z0
z2
z$
z%
z"
z!
z-
z4
z5
z8
z9
z;
z<
#8100
z&
z'
z.
z1
z/
z6
z7
z3
#8500
1)
#9000
1*
#9050
1(
00
12
0$
1%
1"
0!
1-
04
15
08
19
1;
0<
#9100
0.
01
06
07
#9150
1'
0&
1/
13
#9500
1+
#9550
1&
1.
16
#10000
z*
z)
#10050
z(
z0
z2
z$
z%
z"
z!
z-
z4
z5
z8
z9
z;
z<
#10100
z&
z'
z.
z1
z/
z6
z7
z3
#10500
1)
#11000
0*
#11050
0(
10
02
1$
0%
1"
1!
0-
14
05
18
09
1;
1<
#11100
0.
11
06
17
#11150
1'
0&
1/
13
#11500
z*
z)
#11550
z(
z0
z2
z$
z%
z"
z!
z-
z4
z5
z8
z9
z;
z<
#11600
z&
z'
z.
z1
z/
z6
z7
z3
#12000
0)
#12500
1*
#12550
0(
10
02
1$
0%
1"
1!
0-
14
05
18
09
1;
1<
#12600
0.
11
06
17
#12650
1'
0&
1/
13
#13000
z*
z)
#13050
z(
z0
z2
z$
z%
z"
z!
z-
z4
z5
z8
z9
z;
z<
#13100
z&
z'
z.
z1
z/
z6
z7
z3
#13500
0)
#14000
0*
#14050
0(
00
02
0$
0%
0"
0!
0-
04
05
08
09
0;
0<
#14100
1.
01
16
07
#14150
0'
1&
0/
03
#14500
z+
z*
z)
#14550
z'
z&
z.
z1
z(
z0
z2
z$
z%
z"
z!
z6
z7
z-
z4
z5
z8
z9
z;
z<
#14600
z/
z3
