trunk/bench_icarus/th34w2.v
module th34w2(a, b, c, d, th);

input wire a, b, c, d;
output reg th;

initial th <= 1'b0;

wire #10 th_set = ((a&b)|(a&c)|(a&d)|(b&c&d));
wire #10 th_res = ((a==1'b0)&(b==1'b0)&(c==1'b0)&(d==1'b0));

always @(th_set or th_res) begin
	if(th_res) begin
		#10 th <= 1'b0;
	end
	if(th_set) begin
		#10 th <= 1'b1;
	end
end

endmodule

bench_icarus/th23.v
module th23(a, b, c, th);

input wire a, b, c;
output reg th;

initial th <= 0;

wire #10 th_set = ((a&b)|(a&c)|(b&c));
wire #10 th_res = ((a==0)&(b==0)&(c==0));

always @(th_set or th_res) begin
	if(th_res) begin
		#10 th <= 1'b0;
	end 
	if(th_set)begin
		#10 th <= 1'b1;
	end
end

endmodule

trunk/bench_icarus/thfadd.v
module thfadd(x0, x1, y0, y1, ci0, ci1, z0, z1, c0, c1);

input wire x0, x1, y0, y1, ci0, ci1;
output wire z0, z1, c0, c1;


wire w1, w2;

th23 th_0(ci0, x0, y0, w1);
th23 th_1(ci1, x1, y1, w2);

assign c0 = w1;
assign c1 = w2;

//assign z0 = 0;
//assign z1 = 0;

th34w2 th_2(w2, ci0, y0, x0, z0);
th34w2 th_3(w1, ci1, y1, x1, z1);

endmodule

trunk/bench_icarus/bench.v
`timescale 1ns / 100 ps

module testbench();

initial
begin
    $display("begin");

    $dumpfile("test.vcd");
    $dumpvars(0,testbench);
end

//not test
reg [2:0] comb;
reg isnull;

wire z0, z1, c0, c1;
wire ta0 = (isnull == 1) ? 0 : ~comb[0:0];
wire tb0 = (isnull == 1) ? 0 : ~comb[1:1];
wire tc0 = (isnull == 1) ? 0 : ~comb[2:2];

wire #10 ta1 = (isnull == 1) ? 0 : ~ta0;
wire #10 tb1 = (isnull == 1) ? 0 : ~tb0;
wire #10 tc1 = (isnull == 1) ? 0 : ~tc0;


thfadd th_0(ta0, ta1, tb0, tb1, tc0, tc1, z0, z1, c0, c1);

initial
begin
	isnull <=1;
	#50;
	comb <= 3'd0;
	isnull <=0;
	#100;
	isnull <=1;
	#50;
	comb <= 3'd1;
	isnull <=0;
	#100;
	isnull <=1;
	#50;
	comb <= 3'd2;
	isnull <=0;
	#100;
	isnull <=1;
	#50;
	comb <= 3'd3;
	isnull <=0;
	#100;
	isnull <=1;
	#50;
	comb <= 3'd4;
	isnull <=0;
	#100;
	isnull <=1;
	#50;
	comb <= 3'd5;
	isnull <=0;
	#100;
	isnull <=1;
	#50;
	comb <= 3'd6;
	isnull <=0;
	#100;
	isnull <=1;
	#50;
	comb <= 3'd7;
	isnull <=0;
	#100;
	isnull <=1;
	#50;

	
end


endmodule

trunk/bench_icarus/test.vcd
$date
	Mon Mar 02 22:28:57 2015
$end
$version
	Icarus Verilog
$end
$timescale
	100ps
$end
$scope module testbench $end
$var wire 1 ! z1 $end
$var wire 1 " z0 $end
$var wire 1 # tc1 $end
$var wire 1 $ tc0 $end
$var wire 1 % tb1 $end
$var wire 1 & tb0 $end
$var wire 1 ' ta1 $end
$var wire 1 ( ta0 $end
$var wire 1 ) c1 $end
$var wire 1 * c0 $end
$var reg 3 + comb [2:0] $end
$var reg 1 , isnull $end
$scope module th_0 $end
$var wire 1 * c0 $end
$var wire 1 ) c1 $end
$var wire 1 $ ci0 $end
$var wire 1 # ci1 $end
$var wire 1 ( x0 $end
$var wire 1 ' x1 $end
$var wire 1 & y0 $end
$var wire 1 % y1 $end
$var wire 1 ! z1 $end
$var wire 1 " z0 $end
$var wire 1 - w2 $end
$var wire 1 . w1 $end
$scope module th_0 $end
$var wire 1 $ a $end
$var wire 1 ( b $end
$var wire 1 & c $end
$var wire 1 / th_res $end
$var wire 1 0 th_set $end
$var reg 1 . th $end
$upscope $end
$scope module th_1 $end
$var wire 1 # a $end
$var wire 1 ' b $end
$var wire 1 % c $end
$var wire 1 1 th_res $end
$var wire 1 2 th_set $end
$var reg 1 - th $end
$upscope $end
$scope module th_2 $end
$var wire 1 - a $end
$var wire 1 $ b $end
$var wire 1 & c $end
$var wire 1 ( d $end
$var wire 1 3 th_res $end
$var wire 1 4 th_set $end
$var reg 1 " th $end
$upscope $end
$scope module th_3 $end
$var wire 1 . a $end
$var wire 1 # b $end
$var wire 1 % c $end
$var wire 1 ' d $end
$var wire 1 5 th_res $end
$var wire 1 6 th_set $end
$var reg 1 ! th $end
$upscope $end
$upscope $end
$upscope $end
$enddefinitions $end
#0
$dumpvars
x6
x5
x4
x3
x2
x1
x0
x/
0.
0-
1,
bx +
0*
0)
0(
x'
0&
x%
0$
x#
0"
0!
$end
#100
04
13
00
1/
0'
0%
0#
#200
06
15
02
11
#500
1(
1&
1$
0,
b0 +
#600
14
03
10
0/
#700
1"
1*
1.
#800
05
#1500
0(
0&
0$
1,
#1600
04
13
00
1/
#1700
0"
0*
0.
#1800
15
#2000
0(
1&
1$
0,
b1 +
#2100
03
10
0/
1'
#2200
1*
1.
01
05
#2300
16
#2400
1!
#3000
0&
0$
1,
#3100
13
00
1/
0'
#3200
0*
0.
06
11
#3300
15
#3400
0!
#3500
1(
0&
1$
0,
b10 +
#3600
03
10
0/
1%
#3700
1*
1.
05
01
#3800
16
#3900
1!
#4500
0(
0$
1,
#4600
13
00
1/
0%
#4700
0*
0.
06
11
#4800
15
#4900
0!
#5000
0(
1$
0,
b11 +
#5100
03
0/
1'
1%
#5200
05
12
01
#5300
1)
1-
#5400
14
#5500
1"
#6000
0$
1,
#6100
04
1/
0'
0%
#6200
11
15
02
#6300
0)
0-
#6400
13
#6500
1(
1&
0$
0"
0,
b100 +
#6600
03
10
0/
1#
#6700
1*
1.
05
01
#6800
16
#6900
1!
#7500
0(
0&
1,
#7600
1/
13
00
0#
#7700
0*
0.
06
11
#7800
15
#7900
0!
#8000
0(
1&
0,
b101 +
#8100
03
0/
1'
1#
#8200
12
05
01
#8300
1)
1-
#8400
14
#8500
1"
#9000
0&
1,
#9100
04
1/
0'
0#
#9200
15
02
11
#9300
0)
0-
#9400
13
#9500
1(
0&
0"
0,
b110 +
#9600
03
0/
1%
1#
#9700
05
12
01
#9800
1)
1-
#9900
14
#10000
1"
#10500
0(
1,
#10600
04
1/
0%
0#
#10700
15
02
11
#10800
0)
0-
#10900
13
#11000
0(
0"
0,
b111 +
#11100
1'
1%
1#
#11200
16
05
12
01
#11300
1!
1)
1-
#11400
03
#12000
1,
#12100
0'
0%
0#
#12200
06
15
02
11
#12300
0!
0)
0-
#12400
13
