bench_icarus/th34w22.v
module th34w22(a, b, c, d, th);

input wire a, b, c, d;
output reg th;

initial th <= 1'b0;

always @(a or b or c or d) begin
	if((a==1'b0)&&(b==1'b0)&&(c==1'b0)&&(d==1'b0)) begin
		#10 th <= 1'b0;
	end else if((a&b)|(a&c)|(a&d)|(b&c)|(b&d)) begin
		#10 th <= 1'b1;
	end
end

endmodule

bench_icarus/th22.v
module th22(a, b, th);

input wire a, b;
output reg th;

initial th <= 1'b0;

always @(a or b) begin
	if((a==1'b0)&&(b==1'b0)) begin
		#10 th <= 1'b0;
	end else if(a&b) begin
		#10 th <= 1'b1;
	end
end

endmodule

bench_icarus/thand.v
module thand(a0, a1, b0, b1, th0, th1);

input wire a0, a1, b0, b1;
output wire th0, th1;


th22 th22_0(a1, b1, th1);
th34w22 th34w22_0(a0, a1, b1, b0, th0);


/* //и это работает!
assign th1 = a1 & b1;
assign th0 = (a1 & a0) | (b1 & b0) | (a1 & b0) | (b1 & a0) | (a0 & b0);  */

endmodule

trunk/bench_icarus/bench.v
`timescale 1ns / 100 ps

module testbench();

initial
begin
    $display("begin");

    $dumpfile("test.vcd");
    $dumpvars(0,testbench);
end

//not test
reg  ta0,ta1,tb0,tb1;

wire result0, result1;

thand thor_0(ta0, ta1, tb0, tb1, result0, result1);

initial
begin
	ta0 <= 0; // a = null
	ta1 <= 0; //
	tb0 <= 0; // b = null
	tb1 <= 0; //
	#100;
	ta0 <= 1; // a = 0
	ta1 <= 0; //
	tb0 <= 0; // b = null
	tb1 <= 0; //
	#100;
	ta0 <= 1; // a = 0
	ta1 <= 0; //
	tb0 <= 1; // b = 0
	tb1 <= 0; //
	#100;
	ta0 <= 0; // a = null
	ta1 <= 0; //
	tb0 <= 0; // b = null
	tb1 <= 0; //
	#100;
	ta0 <= 1; // a = 0
	ta1 <= 0; //
	tb0 <= 0; // b = null
	tb1 <= 0; //
	#100;
	ta0 <= 1; // a = 0
	ta1 <= 0; //
	tb0 <= 0; // b = 1
	tb1 <= 1; //
	#100;
	ta0 <= 0; // a = null
	ta1 <= 0; //
	tb0 <= 0; // b = null
	tb1 <= 0; //
	#100;
	ta0 <= 0; // a = 1
	ta1 <= 1; //
	tb0 <= 0; // b = null
	tb1 <= 0; //
	#100;
	ta0 <= 0; // a = 1
	ta1 <= 1; //
	tb0 <= 0; // b = 1
	tb1 <= 1; //
	#100;


	
end


endmodule

trunk/bench_icarus/test.vcd
$date
	Mon Mar 02 02:13:41 2015
$end
$version
	Icarus Verilog
$end
$timescale
	100ps
$end
$scope module testbench $end
$var wire 1 ! result1 $end
$var wire 1 " result0 $end
$var reg 1 # ta0 $end
$var reg 1 $ ta1 $end
$var reg 1 % tb0 $end
$var reg 1 & tb1 $end
$scope module thor_0 $end
$var wire 1 # a0 $end
$var wire 1 $ a1 $end
$var wire 1 % b0 $end
$var wire 1 & b1 $end
$var wire 1 ! th1 $end
$var wire 1 " th0 $end
$scope module th22_0 $end
$var wire 1 $ a $end
$var wire 1 & b $end
$var reg 1 ! th $end
$upscope $end
$scope module th34w22_0 $end
$var wire 1 # a $end
$var wire 1 $ b $end
$var wire 1 & c $end
$var wire 1 % d $end
$var reg 1 " th $end
$upscope $end
$upscope $end
$upscope $end
$enddefinitions $end
#0
$dumpvars
0&
0%
0$
0#
0"
0!
$end
#1000
1#
#2000
1%
#2100
1"
#3000
0%
0#
#3100
0"
#4000
1#
#5000
1&
#5100
1"
#6000
0&
0#
#6100
0"
#7000
1$
#8000
1&
#8100
1!
1"
